reproject/wcs_utils.py
reproject/conftest.py
reproject/version.py
reproject/array_utils.py
reproject/compiler_version.abi3.so
reproject/__init__.py
reproject/common.py
reproject/utils.py
reproject/tests/test_utils.py
reproject/tests/__init__.py
reproject/tests/test_array_utils.py
reproject/tests/helpers.py
reproject/tests/test_high_level.py
reproject/tests/data/mwpan2_RGB_3600.hdr
reproject/tests/data/equatorial_3d.fits
reproject/tests/data/gc_ga.hdr
reproject/tests/data/secchi_l0_b.fits
reproject/tests/data/cube.hdr
reproject/tests/data/image_with_distortion_map.fits
reproject/tests/data/generate_asdf.py
reproject/tests/data/aia_171_level1.fits
reproject/tests/data/galactic_2d.fits
reproject/tests/data/secchi_l0_a.fits
reproject/tests/data/gc_eq.hdr
reproject/tests/data/aia_171_level1.asdf
reproject/mosaicking/subset_array.py
reproject/mosaicking/background.py
reproject/mosaicking/__init__.py
reproject/mosaicking/coadd.py
reproject/mosaicking/wcs_helpers.py
reproject/mosaicking/tests/test_coadd.py
reproject/mosaicking/tests/__init__.py
reproject/mosaicking/tests/test_subset_array.py
reproject/mosaicking/tests/test_background.py
reproject/mosaicking/tests/test_wcs_helpers.py
reproject/mosaicking/tests/reference/test_coadd_solar_map.fits
reproject/hips/high_level.py
reproject/hips/_trim_utils.py
reproject/hips/__init__.py
reproject/hips/utils.py
reproject/hips/_dask_array.py
reproject/hips/tests/__init__.py
reproject/hips/tests/test_dask_array.py
reproject/hips/tests/test_high_level.py
reproject/spherical_intersect/_overlap.abi3.so
reproject/spherical_intersect/high_level.py
reproject/spherical_intersect/overlapArea.h
reproject/spherical_intersect/__init__.py
reproject/spherical_intersect/core.py
reproject/spherical_intersect/reproject_slice_c.h
reproject/spherical_intersect/mNaN.h
reproject/spherical_intersect/overlap.py
reproject/spherical_intersect/setup_package.py
reproject-0.19.0.dist-info/RECORD
reproject-0.19.0.dist-info/WHEEL
reproject-0.19.0.dist-info/top_level.txt
reproject-0.19.0.dist-info/METADATA
reproject-0.19.0.dist-info/licenses/LICENSE
