Metadata-Version: 2.4
Name: reproject
Version: 0.19.0
Summary: Reproject astronomical images
Author: Thomas Robitaille, Christoph Deil, Adam Ginsburg, Stuart Mumford, Sam Van Kooten
License: BSD 3-Clause
Project-URL: Homepage, https://reproject.readthedocs.io
Requires-Python: >=3.11
License-File: LICENSE
Requires-Dist: numpy>=1.23
Requires-Dist: astropy>=5.0
Requires-Dist: astropy-healpix>=1.0
Requires-Dist: scipy>=1.9
Requires-Dist: dask[array]>=2024.4.1
Requires-Dist: dask-image>=2025.11.0
Requires-Dist: zarr>=2.17.0
Requires-Dist: fsspec>=2021.9
Requires-Dist: pillow>=10.0
Requires-Dist: pyavm>=0.9.6
Provides-Extra: all
Requires-Dist: shapely; extra == "all"
Provides-Extra: test
Requires-Dist: pytest-astropy; extra == "test"
Requires-Dist: pytest-xdist; extra == "test"
Requires-Dist: tqdm; extra == "test"
Provides-Extra: testall
Requires-Dist: shapely>=2.0.2; extra == "testall"
Requires-Dist: sunpy[map]>=6.0.1; extra == "testall"
Requires-Dist: asdf; extra == "testall"
Requires-Dist: gwcs; extra == "testall"
Requires-Dist: pyvo; extra == "testall"
Provides-Extra: docs
Requires-Dist: sphinx-astropy; extra == "docs"
Requires-Dist: pyvo; extra == "docs"
Requires-Dist: matplotlib; extra == "docs"
Requires-Dist: tqdm; extra == "docs"
Dynamic: license-file
